/*
Copyright (c) Robert O'Callahan <roc@cs.cmu.edu> and Carnegie Mellon University
*/

package ajax.jbc;

public interface OpcodeConstants {
    public static final int OP_nop = 0;
    public static final int OP_aconst_null = 1;
    public static final int OP_iconst_m1 = 2;
    public static final int OP_iconst_0 = 3;
    public static final int OP_iconst_1 = 4;
    public static final int OP_iconst_2 = 5;
    public static final int OP_iconst_3 = 6;
    public static final int OP_iconst_4 = 7;
    public static final int OP_iconst_5 = 8;
    public static final int OP_lconst_0 = 9;
    public static final int OP_lconst_1 = 10;
    public static final int OP_fconst_0 = 11;
    public static final int OP_fconst_1 = 12;
    public static final int OP_fconst_2 = 13;
    public static final int OP_dconst_0 = 14;
    public static final int OP_dconst_1 = 15;
    public static final int OP_bipush = 16;
    public static final int OP_sipush = 17;
    public static final int OP_ldc = 18;
    public static final int OP_ldc_w = 19;
    public static final int OP_ldc2_w = 20;
    public static final int OP_iload = 21;
    public static final int OP_lload = 22;
    public static final int OP_fload = 23;
    public static final int OP_dload = 24;
    public static final int OP_aload = 25;
    public static final int OP_iload_0 = 26;
    public static final int OP_iload_1 = 27;
    public static final int OP_iload_2 = 28;
    public static final int OP_iload_3 = 29;
    public static final int OP_lload_0 = 30;
    public static final int OP_lload_1 = 31;
    public static final int OP_lload_2 = 32;
    public static final int OP_lload_3 = 33;
    public static final int OP_fload_0 = 34;
    public static final int OP_fload_1 = 35;
    public static final int OP_fload_2 = 36;
    public static final int OP_fload_3 = 37;
    public static final int OP_dload_0 = 38;
    public static final int OP_dload_1 = 39;
    public static final int OP_dload_2 = 40;
    public static final int OP_dload_3 = 41;
    public static final int OP_aload_0 = 42;
    public static final int OP_aload_1 = 43;
    public static final int OP_aload_2 = 44;
    public static final int OP_aload_3 = 45;
    public static final int OP_iaload = 46;
    public static final int OP_laload = 47;
    public static final int OP_faload = 48;
    public static final int OP_daload = 49;
    public static final int OP_aaload = 50;
    public static final int OP_baload = 51;
    public static final int OP_caload = 52;
    public static final int OP_saload = 53;
    public static final int OP_istore = 54;
    public static final int OP_lstore = 55;
    public static final int OP_fstore = 56;
    public static final int OP_dstore = 57;
    public static final int OP_astore = 58;
    public static final int OP_istore_0 = 59;
    public static final int OP_istore_1 = 60;
    public static final int OP_istore_2 = 61;
    public static final int OP_istore_3 = 62;
    public static final int OP_lstore_0 = 63;
    public static final int OP_lstore_1 = 64;
    public static final int OP_lstore_2 = 65;
    public static final int OP_lstore_3 = 66;
    public static final int OP_fstore_0 = 67;
    public static final int OP_fstore_1 = 68;
    public static final int OP_fstore_2 = 69;
    public static final int OP_fstore_3 = 70;
    public static final int OP_dstore_0 = 71;
    public static final int OP_dstore_1 = 72;
    public static final int OP_dstore_2 = 73;
    public static final int OP_dstore_3 = 74;
    public static final int OP_astore_0 = 75;
    public static final int OP_astore_1 = 76;
    public static final int OP_astore_2 = 77;
    public static final int OP_astore_3 = 78;
    public static final int OP_iastore = 79;
    public static final int OP_lastore = 80;
    public static final int OP_fastore = 81;
    public static final int OP_dastore = 82;
    public static final int OP_aastore = 83;
    public static final int OP_bastore = 84;
    public static final int OP_castore = 85;
    public static final int OP_sastore = 86;
    public static final int OP_pop = 87;
    public static final int OP_pop2 = 88;
    public static final int OP_dup = 89;
    public static final int OP_dup_x1 = 90;
    public static final int OP_dup_x2 = 91;
    public static final int OP_dup2 = 92;
    public static final int OP_dup2_x1 = 93;
    public static final int OP_dup2_x2 = 94;
    public static final int OP_swap = 95;
    public static final int OP_iadd = 96;
    public static final int OP_ladd = 97;
    public static final int OP_fadd = 98;
    public static final int OP_dadd = 99;
    public static final int OP_isub = 100;
    public static final int OP_lsub = 101;
    public static final int OP_fsub = 102;
    public static final int OP_dsub = 103;
    public static final int OP_imul = 104;
    public static final int OP_lmul = 105;
    public static final int OP_fmul = 106;
    public static final int OP_dmul = 107;
    public static final int OP_idiv = 108;
    public static final int OP_ldiv = 109;
    public static final int OP_fdiv = 110;
    public static final int OP_ddiv = 111;
    public static final int OP_irem = 112;
    public static final int OP_lrem = 113;
    public static final int OP_frem = 114;
    public static final int OP_drem = 115;
    public static final int OP_ineg = 116;
    public static final int OP_lneg = 117;
    public static final int OP_fneg = 118;
    public static final int OP_dneg = 119;
    public static final int OP_ishl = 120;
    public static final int OP_lshl = 121;
    public static final int OP_ishr = 122;
    public static final int OP_lshr = 123;
    public static final int OP_iushr = 124;
    public static final int OP_lushr = 125;
    public static final int OP_iand = 126;
    public static final int OP_land = 127;
    public static final int OP_ior = 128;
    public static final int OP_lor = 129;
    public static final int OP_ixor = 130;
    public static final int OP_lxor = 131;
    public static final int OP_iinc = 132;
    public static final int OP_i2l = 133;
    public static final int OP_i2f = 134;
    public static final int OP_i2d = 135;
    public static final int OP_l2i = 136;
    public static final int OP_l2f = 137;
    public static final int OP_l2d = 138;
    public static final int OP_f2i = 139;
    public static final int OP_f2l = 140;
    public static final int OP_f2d = 141;
    public static final int OP_d2i = 142;
    public static final int OP_d2l = 143;
    public static final int OP_d2f = 144;
    public static final int OP_i2b = 145;
    public static final int OP_i2c = 146;
    public static final int OP_i2s = 147;
    public static final int OP_lcmp = 148;
    public static final int OP_fcmpl = 149;
    public static final int OP_fcmpg = 150;
    public static final int OP_dcmpl = 151;
    public static final int OP_dcmpg = 152;
    public static final int OP_ifeq = 153;
    public static final int OP_ifne = 154;
    public static final int OP_iflt = 155;
    public static final int OP_ifge = 156;
    public static final int OP_ifgt = 157;
    public static final int OP_ifle = 158;
    public static final int OP_if_icmpeq = 159;
    public static final int OP_if_icmpne = 160;
    public static final int OP_if_icmplt = 161;
    public static final int OP_if_icmpge = 162;
    public static final int OP_if_icmpgt = 163;
    public static final int OP_if_icmple = 164;
    public static final int OP_if_acmpeq = 165;
    public static final int OP_if_acmpne = 166;
    public static final int OP_goto = 167;
    public static final int OP_jsr = 168;
    public static final int OP_ret = 169;
    public static final int OP_tableswitch = 170;
    public static final int OP_lookupswitch = 171;
    public static final int OP_ireturn = 172;
    public static final int OP_lreturn = 173;
    public static final int OP_freturn = 174;
    public static final int OP_dreturn = 175;
    public static final int OP_areturn = 176;
    public static final int OP_return = 177;
    public static final int OP_getstatic = 178;
    public static final int OP_putstatic = 179;
    public static final int OP_getfield = 180;
    public static final int OP_putfield = 181;
    public static final int OP_invokevirtual = 182;
    public static final int OP_invokespecial = 183;
    public static final int OP_invokestatic = 184;
    public static final int OP_invokeinterface = 185;
    public static final int OP_new = 187;
    public static final int OP_newarray = 188;
    public static final int OP_anewarray = 189;
    public static final int OP_arraylength = 190;
    public static final int OP_athrow = 191;
    public static final int OP_checkcast = 192;
    public static final int OP_instanceof = 193;
    public static final int OP_monitorenter = 194;
    public static final int OP_monitorexit = 195;
    public static final int OP_wide = 196;
    public static final int OP_multianewarray = 197;
    public static final int OP_ifnull = 198;
    public static final int OP_ifnonnull = 199;
    public static final int OP_goto_w = 200;
    public static final int OP_jsr_w = 201;
}
